person_swap/__init__.py
person_swap/admin.py
person_swap/apps.py
person_swap/runner.py
person_swap/views.py
person_swap/convertion/__init__.py
person_swap/convertion/face_utils/__init__.py
person_swap/convertion/face_utils/face_detect_crop.py
person_swap/convertion/face_utils/nn_modules.py
person_swap/convertion/face_utils/models/__init__.py
person_swap/convertion/face_utils/models/arc_margin_model.py
person_swap/convertion/face_utils/models/fs_model.py
person_swap/convertion/face_utils/models/fs_networks.py
person_swap/convertion/models/__init__.py
person_swap/convertion/models/face_swap_model.py
person_swap/convertion/voice_utils/__init__.py
person_swap/convertion/voice_utils/speech_to_text.py
person_swap/convertion/voice_utils/voice_cloning.py
person_swap/custom_utils/__init__.py
person_swap/custom_utils/conversion_exception.py
person_swap/custom_utils/device.py
person_swap/custom_utils/logger.py
person_swap/forms/__init__.py
person_swap/forms/conversion_forms.py
person_swap/forms/forms.py
person_swap/forms/model_forms.py
person_swap/migrations/0001_initial.py
person_swap/migrations/__init__.py
person_swap/models/__init__.py
person_swap/models/abstract_file.py
person_swap/models/file.py
person_swap/models/model.py
person_swap/tests/__init__.py
person_swap/tests/integration/__init__.py
person_swap/tests/integration/test_image_conversion.py
person_swap/tests/integration/test_video_conversion.py
person_swap/tests/integration/test_views.py
person_swap/tests/stress_testing/__init__.py
person_swap/tests/stress_testing/test_face_conversion.py
person_swap/tests/unit/__init__.py
person_swap/tests/unit/test_admin.py
person_swap/tests/unit/test_forms.py
person_swap-1.0.0.dist-info/LICENSE
person_swap-1.0.0.dist-info/METADATA
person_swap-1.0.0.dist-info/WHEEL
person_swap-1.0.0.dist-info/top_level.txt
person_swap-1.0.0.dist-info/RECORD
