Metadata-Version: 2.1
Name: person-swap
Version: 1.0.0
Summary: TODO
Home-page: https://github.com/Segal011/person-swap
Author: Indre.Segal
Author-email: indre.segal@gmail.com
Project-URL: Bug Tracker, https://github.com/Segal011/person-swap/issues
Classifier: Programming Language :: Python :: 3
Classifier: License :: OSI Approved :: MIT License
Classifier: Operating System :: OS Independent
Requires-Python: >=3.7
License-File: LICENSE
